BlueTest/YApi2Csv.py
BlueTest/__init__.py
BlueTest/__version__.py
BlueTest/core.py
BlueTest/dome_test.py
BlueTest/logInit.py
BlueTest/parm.py
BlueTest/press.py
BlueTest/toolbox.py
BlueTest/Report/HTMLReport.py
BlueTest/Report/__init__.py
BlueTest/Report/demo.py
BlueTest/Report/mould.py
BlueTest/Report/report.py
BlueTest-0.3.6.dist-info/LICENSE.txt
BlueTest-0.3.6.dist-info/METADATA
BlueTest-0.3.6.dist-info/WHEEL
BlueTest-0.3.6.dist-info/top_level.txt
BlueTest-0.3.6.dist-info/RECORD
